README.rst
setup.py
easyirc/__init__.py
easyirc/connection.py
easyirc/const.py
easyirc/exception.py
easyirc/model.py
easyirc/settingloader.py
easyirc/socket.py
easyirc/storage.py
easyirc/util.py
easyirc/version.txt
easyirc.egg-info/PKG-INFO
easyirc.egg-info/SOURCES.txt
easyirc.egg-info/dependency_links.txt
easyirc.egg-info/requires.txt
easyirc.egg-info/top_level.txt
easyirc/client/__init__.py
easyirc/client/bot.py
easyirc/command/__init__.py
easyirc/command/client.py
easyirc/command/interactive.py
easyirc/command/protocol.py
easyirc/event/__init__.py
easyirc/event/bot.py
easyirc/event/protocol.py