Metadata-Version: 1.0
Name: easyirc
Version: 0.0.8
Summary: Easy IRC is an IRC toolkit to develop IRC client or bot, especially for Python/IRC beginner.
Home-page: https://github.com/youknowone/easyirc
Author: Jeong YunWon
Author-email: jeong+easyirc@youknowone.org
License: UNKNOWN
Platform: UNKNOWN
